digraph G {
  node [style=filled,color=".3 .2 1.0",shape=box,];
  "Entry";
  "0: x = 1";
  "1: %intconst0 = 3";
  "2: y = x << %intconst0";
  "3: goto 21";
  "4: nop";
  "5: %intconst1 = 2";
  "6: invokevirtual %this.use(%intconst1)@<UnreachableSwitchBranch: void lookupSwitch()>:6(@L8)";
  "7: goto 24";
  "8: nop";
  "9: %intconst2 = 4";
  "10: invokevirtual %this.use(%intconst2)@<UnreachableSwitchBranch: void lookupSwitch()>:10(@L11)";
  "11: goto 24";
  "12: nop";
  "13: %intconst3 = 8";
  "14: invokevirtual %this.use(%intconst3)@<UnreachableSwitchBranch: void lookupSwitch()>:14(@L14)";
  "15: goto 24";
  "16: nop";
  "17: %intconst4 = 666";
  "18: invokevirtual %this.use(%intconst4)@<UnreachableSwitchBranch: void lookupSwitch()>:18(@L17)";
  "19: goto 24";
  "20: goto 24";
  "21: nop";
  "22: nop";
  "23: lookupswitch (y) {2->4, 4->8, 8->12, default->16}";
  "24: nop";
  "25: return";
  "Exit";
  "Entry" -> "0: x = 1" [label="ENTRY",];
  "0: x = 1" -> "1: %intconst0 = 3" [label="FALL_THROUGH",];
  "1: %intconst0 = 3" -> "2: y = x << %intconst0" [label="FALL_THROUGH",];
  "2: y = x << %intconst0" -> "3: goto 21" [label="FALL_THROUGH",];
  "3: goto 21" -> "21: nop" [label="GOTO",];
  "4: nop" -> "5: %intconst1 = 2" [label="FALL_THROUGH",];
  "5: %intconst1 = 2" -> "6: invokevirtual %this.use(%intconst1)@<UnreachableSwitchBranch: void lookupSwitch()>:6(@L8)" [label="FALL_THROUGH",];
  "6: invokevirtual %this.use(%intconst1)@<UnreachableSwitchBranch: void lookupSwitch()>:6(@L8)" -> "7: goto 24" [label="FALL_THROUGH",];
  "7: goto 24" -> "24: nop" [label="GOTO",];
  "8: nop" -> "9: %intconst2 = 4" [label="FALL_THROUGH",];
  "9: %intconst2 = 4" -> "10: invokevirtual %this.use(%intconst2)@<UnreachableSwitchBranch: void lookupSwitch()>:10(@L11)" [label="FALL_THROUGH",];
  "10: invokevirtual %this.use(%intconst2)@<UnreachableSwitchBranch: void lookupSwitch()>:10(@L11)" -> "11: goto 24" [label="FALL_THROUGH",];
  "11: goto 24" -> "24: nop" [label="GOTO",];
  "12: nop" -> "13: %intconst3 = 8" [label="FALL_THROUGH",];
  "13: %intconst3 = 8" -> "14: invokevirtual %this.use(%intconst3)@<UnreachableSwitchBranch: void lookupSwitch()>:14(@L14)" [label="FALL_THROUGH",];
  "14: invokevirtual %this.use(%intconst3)@<UnreachableSwitchBranch: void lookupSwitch()>:14(@L14)" -> "15: goto 24" [label="FALL_THROUGH",];
  "15: goto 24" -> "24: nop" [label="GOTO",];
  "16: nop" -> "17: %intconst4 = 666" [label="FALL_THROUGH",];
  "17: %intconst4 = 666" -> "18: invokevirtual %this.use(%intconst4)@<UnreachableSwitchBranch: void lookupSwitch()>:18(@L17)" [label="FALL_THROUGH",];
  "18: invokevirtual %this.use(%intconst4)@<UnreachableSwitchBranch: void lookupSwitch()>:18(@L17)" -> "19: goto 24" [label="FALL_THROUGH",];
  "19: goto 24" -> "24: nop" [label="GOTO",];
  "20: goto 24" -> "24: nop" [label="GOTO",];
  "21: nop" -> "22: nop" [label="FALL_THROUGH",];
  "22: nop" -> "23: lookupswitch (y) {2->4, 4->8, 8->12, default->16}" [label="FALL_THROUGH",];
  "23: lookupswitch (y) {2->4, 4->8, 8->12, default->16}" -> "4: nop" [label="SWITCH_CASE
[case 2]",];
  "23: lookupswitch (y) {2->4, 4->8, 8->12, default->16}" -> "8: nop" [label="SWITCH_CASE
[case 4]",];
  "23: lookupswitch (y) {2->4, 4->8, 8->12, default->16}" -> "12: nop" [label="SWITCH_CASE
[case 8]",];
  "23: lookupswitch (y) {2->4, 4->8, 8->12, default->16}" -> "16: nop" [label="SWITCH_DEFAULT",];
  "24: nop" -> "25: return" [label="FALL_THROUGH",];
  "25: return" -> "Exit" [label="RETURN",];
}
